AUTHORS
LICENSE
README.rst
cliform/__init__.py
cliform/core.py
peltak/__init__.py
peltak/cli/__init__.py
peltak/cli/git.py
peltak/cli/git_impl.py
peltak/cli/peltak.py
peltak/cli/peltak_impl.py
peltak/cli/scripts.py
peltak/cli/version.py
peltak/core/__init__.py
peltak/core/conf.py
peltak/core/context.py
peltak/core/exc.py
peltak/core/fs.py
peltak/core/git/__init__.py
peltak/core/git/branch.py
peltak/core/git/status.py
peltak/core/git/types.py
peltak/core/git/util.py
peltak/core/hooks.py
peltak/core/log.py
peltak/core/scripts/__init__.py
peltak/core/scripts/loader.py
peltak/core/scripts/logic.py
peltak/core/scripts/types.py
peltak/core/shell.py
peltak/core/templates/__init__.py
peltak/core/templates/engine.py
peltak/core/templates/filters.py
peltak/core/types.py
peltak/core/util.py
peltak/core/versioning/__init__.py
peltak/core/versioning/version_file.py
peltak/main.py
peltak/templates/peltak-js.yaml
peltak/templates/peltak-py.yaml
peltak/testing/__init__.py
peltak/testing/fixtures.py
peltak/testing/mocks.py
peltak/testing/patches.py
peltak/testing/util.py
peltak-0.31.1.dist-info/AUTHORS
peltak-0.31.1.dist-info/LICENSE
peltak-0.31.1.dist-info/METADATA
peltak-0.31.1.dist-info/WHEEL
peltak-0.31.1.dist-info/entry_points.txt
peltak-0.31.1.dist-info/RECORD
