Metadata-Version: 2.1
Name: peltak
Version: 0.31.1
Summary: A command line tool to help manage a project
Home-page: http://novopl.github.com/peltak
License: Apache 2.0
Author: Mateusz Klos
Author-email: novopl@gmail.com
Requires-Python: >=3.7.2,<4.0
Classifier: Development Status :: 4 - Beta
Classifier: Intended Audience :: Developers
Classifier: License :: OSI Approved :: MIT License
Classifier: License :: Other/Proprietary License
Classifier: Programming Language :: Python
Classifier: Programming Language :: Python :: 3
Classifier: Programming Language :: Python :: 3.8
Classifier: Programming Language :: Python :: 3.9
Classifier: Programming Language :: Python :: 3.10
Classifier: Programming Language :: Python :: 3.11
Classifier: Programming Language :: Python :: 3.12
Classifier: Topic :: Utilities
Requires-Dist: PyYAML (>=6.0)
Requires-Dist: click (>=8.0,<9.0)
Requires-Dist: jinja2 (>=2.12)
Requires-Dist: pygments (>=2.7.4)
Requires-Dist: tomlkit (>=0.7.0)
Project-URL: Documentation, http://novopl.github.com/peltak
Project-URL: Repository, http://github.com/novopl/peltak
